fastcgi/__init__.py
fastcgi/_nbdev.py
fastcgi/core.py
fastcgi/decorator.py
fastcgi/http.py
fastcgi-0.0.3.dist-info/LICENSE
fastcgi-0.0.3.dist-info/METADATA
fastcgi-0.0.3.dist-info/WHEEL
fastcgi-0.0.3.dist-info/entry_points.txt
fastcgi-0.0.3.dist-info/top_level.txt
fastcgi-0.0.3.dist-info/RECORD
