Metadata-Version: 2.1
Name: fastcgi
Version: 0.0.3
Summary: A fastcgi handler for Python's `socketserver` classes
Home-page: https://github.com/fastai/fastcgi/tree/master/
Author: Jeremy Howard
Author-email: info@fast.ai
License: Apache Software License 2.0
Keywords: fastcgi python http socketserver server
Platform: UNKNOWN
Classifier: Development Status :: 4 - Beta
Classifier: Intended Audience :: Developers
Classifier: License :: OSI Approved :: Apache Software License
Classifier: Natural Language :: English
Classifier: Programming Language :: Python :: 3.6
Classifier: Programming Language :: Python :: 3.7
Classifier: Programming Language :: Python :: 3.8
Requires-Python: >=3.6
Provides-Extra: dev
